rq_retry/__init__.py
rq_retry/queue.py
rq_retry/worker.py
rq_retry-0.3.0.dist-info/DESCRIPTION.rst
rq_retry-0.3.0.dist-info/METADATA
rq_retry-0.3.0.dist-info/metadata.json
rq_retry-0.3.0.dist-info/pbr.json
rq_retry-0.3.0.dist-info/RECORD
rq_retry-0.3.0.dist-info/top_level.txt
rq_retry-0.3.0.dist-info/WHEEL
